[
    { "id": "cabinet-dr-caligari",       "label": "The Cabinet of Dr. Caligari",                          "date": 1920 },
    { "id": "nosferatu",                 "label": "Nosferatu",                                           "date": 1922 },
    { "id": "phantom-opera",             "label": "The Phantom of the Opera",                              "date": 1925 },
    { "id": "dracula-1931",              "label": "Dracula",                                             "date": 1931 },
    { "id": "frankenstein-1931",         "label": "Frankenstein",                                        "date": 1931 },
    { "id": "m-1931",                    "label": "M",                                                   "date": 1931 },
    { "id": "white-zombie",              "label": "White Zombie",                                        "date": 1932 },
    { "id": "invisible-man",             "label": "The Invisible Man",                                    "date": 1933 },
    { "id": "bride-of-frankenstein",     "label": "Bride of Frankenstein",                                "date": 1935 },
    { "id": "freaks-1936",               "label": "Freaks",                                              "date": 1936 },
    { "id": "wolf-man-1941",             "label": "The Wolf Man",                                        "date": 1941 },
    { "id": "dead-of-night-1945",        "label": "Dead of Night",                                       "date": 1945 },
    { "id": "house-of-wax-1953",         "label": "House of Wax",                                        "date": 1953 },
    { "id": "black-lagoon-1954",         "label": "Creature from the Black Lagoon",                        "date": 1954 },
    { "id": "body-snatchers-1956",       "label": "Invasion of the Body Snatchers",                        "date": 1956 },
    { "id": "horror-of-dracula-1958",    "label": "Horror of Dracula",                                     "date": 1958 },
    { "id": "psycho-1960",               "label": "Psycho",                                              "date": 1960 },
    { "id": "baby-jane-1962",            "label": "Whatever Happened to Baby Jane?",                       "date": 1962 },
    { "id": "haunting-1963",             "label": "The Haunting",                                        "date": 1963 },
    { "id": "witchfinder-1964",          "label": "Witchfinder General",                                 "date": 1964 },
    { "id": "repulsion-1965",            "label": "Repulsion",                                          "date": 1965 },
    { "id": "night-dead-1968",           "label": "Night of the Living Dead",                             "date": 1968 },
    { "id": "rosemarys-baby-1968",       "label": "Rosemary’s Baby",                                     "date": 1968 },
    { "id": "exorcist-1973",             "label": "The Exorcist",                                        "date": 1973 },
    { "id": "texas-chain-saw-1974",      "label": "The Texas Chain Saw Massacre",                        "date": 1974 },
    { "id": "jaws-1975",                  "label": "Jaws",                                                "date": 1975 },
    { "id": "carrie-1976",                "label": "Carrie",                                              "date": 1976 },
    { "id": "omen-1976",                  "label": "The Omen",                                            "date": 1976 },
    { "id": "suspiria-1977",              "label": "Suspiria",                                           "date": 1977 },
    { "id": "halloween-1978",             "label": "Halloween",                                          "date": 1978 },
    { "id": "dawn-dead-1978",             "label": "Dawn of the Dead",                                   "date": 1978 },
    { "id": "alien-1979",                 "label": "Alien",                                              "date": 1979 },
    { "id": "shining-1980",               "label": "The Shining",                                        "date": 1980 },
    { "id": "friday-13th-1980",           "label": "Friday the 13th",                                    "date": 1980 },
    { "id": "werewolf-london-1981",       "label": "An American Werewolf in London",                     "date": 1981 },
    { "id": "evil-dead-1981",             "label": "The Evil Dead (original)",                                      "date": 1981 },
    { "id": "poltergeist-1982",           "label": "Poltergeist",                                        "date": 1982 },
    { "id": "elm-street-1984",            "label": "A Nightmare on Elm Street",                          "date": 1984 },
    { "id": "re-animator-1985",           "label": "Re-Animator",                                        "date": 1985 },
    { "id": "aliens-1986",                "label": "Aliens",                                             "date": 1986 },
    { "id": "fly-1986",                   "label": "The Fly",                                           "date": 1986 },
    { "id": "hellraiser-1987",            "label": "Hellraiser",                                        "date": 1987 },
    { "id": "childs-play-1988",           "label": "Child’s Play",                                      "date": 1988 },
    { "id": "pet-sematary-1989",          "label": "Pet Sematary",                                      "date": 1989 },
    { "id": "misery-1990",                "label": "Misery",                                            "date": 1990 },
    { "id": "silence-lambs-1991",         "label": "The Silence of the Lambs",                         "date": 1991 },
    { "id": "dracula-1992",               "label": "Bram Stoker’s Dracula",                             "date": 1992 },
    { "id": "interview-vampire-1994",     "label": "Interview with the Vampire",                        "date": 1994 },
    { "id": "scream-1996",                "label": "Scream",                                            "date": 1996 },
    { "id": "event-horizon-1997",         "label": "Event Horizon",                                     "date": 1997 },
    { "id": "blair-witch-1998",           "label": "The Blair Witch Project",                          "date": 1998 },
    { "id": "sixth-sense-1999",           "label": "The Sixth Sense",                                   "date": 1999 },
    { "id": "american-psycho-2000",       "label": "American Psycho",                                  "date": 2000 },
    { "id": "final-destination-2000",     "label": "Final Destination",                                "date": 2000 },
    { "id": "others-2001",                "label": "The Others",                                       "date": 2001 },
    { "id": "28-days-later-2002",         "label": "28 Days Later",                                    "date": 2002 },
    { "id": "ring-2002",                  "label": "The Ring",                                         "date": 2002 },
    { "id": "house-1000-corpses-2003",    "label": "House of 1000 Corpses",                            "date": 2003 },
    { "id": "saw-2004",                   "label": "Saw",                                              "date": 2004 },
    { "id": "shaun-of-dead-2004",         "label": "Shaun of the Dead",                                "date": 2004 },
    { "id": "descent-2005",               "label": "The Descent",                                      "date": 2005 },
    { "id": "pans-labyrinth-2006",        "label": "Pan’s Labyrinth",                                  "date": 2006 },
    { "id": "rec-2007",                   "label": "[REC]",                                          "date": 2007 },
    { "id": "paranormal-activity-2007",   "label": "Paranormal Activity",                             "date": 2007 },
    { "id": "let-right-one-in-2008",      "label": "Let the Right One In",                            "date": 2008 },
    { "id": "cloverfield-2008",           "label": "Cloverfield",                                     "date": 2008 },
    { "id": "drag-me-to-hell-2009",       "label": "Drag Me to Hell",                                 "date": 2009 },
    { "id": "insidious-2010",             "label": "Insidious",                                       "date": 2010 },
    { "id": "let-me-in-2010",             "label": "Let Me In",                                       "date": 2010 },
    { "id": "cabin-in-woods-2011",        "label": "The Cabin in the Woods",                          "date": 2011 },
    { "id": "sinister-2012",              "label": "Sinister",                                        "date": 2012 },
    { "id": "conjuring-2013",             "label": "The Conjuring",                                   "date": 2013 },
    { "id": "evil-dead-2013",             "label": "Evil Dead (remake)",                                       "date": 2013 },
    { "id": "it-follows-2014",            "label": "It Follows",                                      "date": 2014 },
    { "id": "witch-2015",                 "label": "The Witch",                                       "date": 2015 },
    { "id": "visit-2015",                 "label": "The Visit",                                       "date": 2015 },
    { "id": "dont-breathe-2016",          "label": "Don’t Breathe",                                   "date": 2016 },
    { "id": "raw-2016",                   "label": "Raw",                                             "date": 2016 },
    { "id": "get-out-2017",               "label": "Get Out",                                        "date": 2017 },
    { "id": "ritual-2017",                "label": "The Ritual",                                      "date": 2017 },
    { "id": "a-quiet-place-2018",         "label": "A Quiet Place",                                  "date": 2018 },
    { "id": "hereditary-2018",            "label": "Hereditary",                                     "date": 2018 },
    { "id": "midsommar-2019",             "label": "Midsommar",                                      "date": 2019 },
    { "id": "us-2019",                    "label": "Us",                                              "date": 2019 },
    { "id": "invisible-man-2020",         "label": "The Invisible Man",                              "date": 2020 },
    { "id": "quiet-place-2-2021",         "label": "A Quiet Place Part II",                          "date": 2021 },
    { "id": "candyman-2021",              "label": "Candyman",                                       "date": 2021 },
    { "id": "malignant-2021",             "label": "Malignant",                                      "date": 2021 },
    { "id": "barbarian-2022",             "label": "Barbarian",                                      "date": 2022 },
    { "id": "smile-2022",                 "label": "Smile",                                          "date": 2022 },
    { "id": "nope-2022",                  "label": "Nope",                                           "date": 2022 },
    { "id": "talk-to-me-2023",            "label": "Talk to Me",                                     "date": 2023 },
    { "id": "evil-dead-rise-2023",        "label": "Evil Dead Rise",                                 "date": 2023 },
    { "id": "saw-x-2023",                 "label": "Saw X",                                          "date": 2023 },
    { "id": "youre-next-2013",            "label": "You’re Next",                                    "date": 2013 },
    { "id": "x-2022",                     "label": "X",                                              "date": 2022 }
  ]
  